{
  "main": {
    "id": "4186c78678f2d960",
    "type": "split",
    "children": [
      {
        "id": "097c68d8089fb712",
        "type": "tabs",
        "children": [
          {
            "id": "6a25a283e475b785",
            "type": "leaf",
            "state": {
              "type": "empty",
              "state": {},
              "icon": "lucide-file",
              "title": "新标签页"
            }
          }
        ]
      }
    ],
    "direction": "vertical"
  },
  "left": {
    "id": "89f90223469e7c5c",
    "type": "split",
    "children": [
      {
        "id": "0dc31d9a4f75b562",
        "type": "tabs",
        "children": [
          {
            "id": "cc3b402b102b9c98",
            "type": "leaf",
            "state": {
              "type": "file-explorer",
              "state": {
                "sortOrder": "alphabetical",
                "autoReveal": false
              },
              "icon": "lucide-folder-closed",
              "title": "文件列表"
            }
          },
          {
            "id": "d986130dd1997266",
            "type": "leaf",
            "state": {
              "type": "search",
              "state": {
                "query": "",
                "matchingCase": false,
                "explainSearch": false,
                "collapseAll": false,
                "extraContext": false,
                "sortOrder": "alphabetical"
              },
              "icon": "lucide-search",
              "title": "搜索"
            }
          },
          {
            "id": "1ad4750b2458ae73",
            "type": "leaf",
            "state": {
              "type": "bookmarks",
              "state": {},
              "icon": "lucide-bookmark",
              "title": "书签"
            }
          }
        ]
      }
    ],
    "direction": "horizontal",
    "width": 300
  },
  "right": {
    "id": "f6af95d8081bcf3a",
    "type": "split",
    "children": [
      {
        "id": "1eb4e338b7612719",
        "type": "tabs",
        "children": [
          {
            "id": "c4a119c4afb9ae30",
            "type": "leaf",
            "state": {
              "type": "backlink",
              "state": {
                "collapseAll": false,
                "extraContext": false,
                "sortOrder": "alphabetical",
                "showSearch": false,
                "searchQuery": "",
                "backlinkCollapsed": false,
                "unlinkedCollapsed": true
              },
              "icon": "links-coming-in",
              "title": "反向链接"
            }
          },
          {
            "id": "d2a76f79d6edc55b",
            "type": "leaf",
            "state": {
              "type": "outgoing-link",
              "state": {
                "linksCollapsed": false,
                "unlinkedCollapsed": true
              },
              "icon": "links-going-out",
              "title": "出链"
            }
          },
          {
            "id": "be2f3eae262b6b52",
            "type": "leaf",
            "state": {
              "type": "tag",
              "state": {
                "sortOrder": "frequency",
                "useHierarchy": true,
                "showSearch": false,
                "searchQuery": ""
              },
              "icon": "lucide-tags",
              "title": "标签"
            }
          },
          {
            "id": "3ff1f00bc9a84d44",
            "type": "leaf",
            "state": {
              "type": "outline",
              "state": {
                "followCursor": false,
                "showSearch": false,
                "searchQuery": ""
              },
              "icon": "lucide-list",
              "title": "大纲"
            }
          }
        ]
      }
    ],
    "direction": "horizontal",
    "width": 300,
    "collapsed": true
  },
  "left-ribbon": {
    "hiddenItems": {
      "switcher:打开快速切换": false,
      "graph:查看关系图谱": false,
      "canvas:新建白板": false,
      "daily-notes:打开/创建今天的日记": false,
      "templates:插入模板": false,
      "command-palette:打开命令面板": false
    }
  },
  "active": "6a25a283e475b785",
  "lastOpenFiles": []
}